pyache.py
pyache-0.2.0.dist-info/LICENSE
pyache-0.2.0.dist-info/METADATA
pyache-0.2.0.dist-info/WHEEL
pyache-0.2.0.dist-info/top_level.txt
pyache-0.2.0.dist-info/RECORD
