Metadata-Version: 2.1
Name: pyache
Version: 0.2.0
Summary: A simple numpy caching library
Home-page: https://github.com/mycroftai/pyache
Author: Mycroft AI
Author-email: dev@mycroft.ai
Maintainer: Matthew Scholefield
Maintainer-email: matthew331199@gmail.com
License: Apache2.0
Platform: UNKNOWN
Requires-Dist: numpy
